NOTICE
splunk_add_on_ucc_modinput_test/__init__.py
splunk_add_on_ucc_modinput_test/__main__.py
splunk_add_on_ucc_modinput_test/commands.py
splunk_add_on_ucc_modinput_test/common/__init__.py
splunk_add_on_ucc_modinput_test/common/bootstrap.py
splunk_add_on_ucc_modinput_test/common/splunk_instance.py
splunk_add_on_ucc_modinput_test/common/splunk_service_pool.py
splunk_add_on_ucc_modinput_test/common/ta_base.py
splunk_add_on_ucc_modinput_test/common/utils.py
splunk_add_on_ucc_modinput_test/functional/__init__.py
splunk_add_on_ucc_modinput_test/functional/common/__init__.py
splunk_add_on_ucc_modinput_test/functional/common/identifier_factory.py
splunk_add_on_ucc_modinput_test/functional/common/pytest_config_adapter.py
splunk_add_on_ucc_modinput_test/functional/common/splunk_instance_file.py
splunk_add_on_ucc_modinput_test/functional/common/splunk_instance_kvstore.py
splunk_add_on_ucc_modinput_test/functional/constants.py
splunk_add_on_ucc_modinput_test/functional/decorators.py
splunk_add_on_ucc_modinput_test/functional/entities/__init__.py
splunk_add_on_ucc_modinput_test/functional/entities/collections.py
splunk_add_on_ucc_modinput_test/functional/entities/executable.py
splunk_add_on_ucc_modinput_test/functional/entities/forge.py
splunk_add_on_ucc_modinput_test/functional/entities/task.py
splunk_add_on_ucc_modinput_test/functional/entities/test.py
splunk_add_on_ucc_modinput_test/functional/exceptions.py
splunk_add_on_ucc_modinput_test/functional/executor.py
splunk_add_on_ucc_modinput_test/functional/manager.py
splunk_add_on_ucc_modinput_test/functional/pytest_plugin/__init__.py
splunk_add_on_ucc_modinput_test/functional/pytest_plugin/hooks.py
splunk_add_on_ucc_modinput_test/functional/pytest_plugin/options.py
splunk_add_on_ucc_modinput_test/functional/pytest_plugin/utils.py
splunk_add_on_ucc_modinput_test/functional/splunk/__init__.py
splunk_add_on_ucc_modinput_test/functional/splunk/client.py
splunk_add_on_ucc_modinput_test/functional/splunk/configuration.py
splunk_add_on_ucc_modinput_test-2.0.5.dist-info/LICENSE
splunk_add_on_ucc_modinput_test-2.0.5.dist-info/METADATA
splunk_add_on_ucc_modinput_test-2.0.5.dist-info/WHEEL
splunk_add_on_ucc_modinput_test-2.0.5.dist-info/entry_points.txt
splunk_add_on_ucc_modinput_test-2.0.5.dist-info/RECORD
